{
  "last_updated": "2026-02-01T01:27:57+00:00",
  "current": {
    "subscribers": 742,
    "views": 852435,
    "videos": 537
  },
  "rolling": {
    "subs_per_day_7": -0.14285714285714285,
    "subs_per_day_30": 0.1,
    "views_per_day_7": 63.0,
    "views_per_day_30": 15.933333333333334
  },
  "ratios": {
    "views_per_video": 1587.4022346368715,
    "views_per_sub": 1148.83423180593,
    "subs_per_video": 1.3817504655493482
  },
  "projection": {
    "slope_subs_per_day": 0.0860665752388072,
    "next_50": {
      "target": 750,
      "eta_days": 92.95129936101861,
      "eta_date": "2026-05-05T00:17:49.264792007+00:00"
    },
    "next_100": {
      "target": 800,
      "eta_days": 673.896920367385,
      "eta_date": "2027-12-06T22:59:30.919742064+00:00"
    },
    "to_1000": {
      "target": 1000,
      "eta_days": 2997.6794043928503,
      "eta_date": "2034-04-17T17:46:17.539542265+00:00"
    }
  },
  "source_csv": "docs/youtube/youtube-history-summed.csv",
  "outputs": {
    "enriched_csv": "data/metrics/youtube_enriched.csv",
    "summary_json": "data/metrics/youtube_summary.json"
  }
}