{
  "Main": { "date": "2026-04-14 01:49:16 UTC", "videos": 177, "subscribers": 413, "views": 528224 },
  "Fortnite": { "date": "2026-04-14 01:49:16 UTC", "videos": 267, "subscribers": 268, "views": 269006 },
  "Troubleshooting": { "date": "2026-04-14 01:49:16 UTC", "videos": 17, "subscribers": 44, "views": 29951 },
  "Adamsmr": { "date": "2026-04-14 01:49:16 UTC", "videos": 63, "subscribers": 19, "views": 22922 },
  "AJ_Studios": { "date": "2026-04-14 01:49:16 UTC", "videos": 17, "subscribers": 7, "views": 11270 },
  "lokismr": { "date": "2026-04-14 01:49:16 UTC", "videos": 17, "subscribers": 21, "views": 22558 }
}
