{
  "Main": { "date": "2026-06-08 02:46:38 UTC", "videos": 177, "subscribers": 419, "views": 532738 },
  "Fortnite": { "date": "2026-06-08 02:46:38 UTC", "videos": 267, "subscribers": 266, "views": 269061 },
  "Troubleshooting": { "date": "2026-06-08 02:46:38 UTC", "videos": 18, "subscribers": 45, "views": 30160 },
  "Adamsmr": { "date": "2026-06-08 02:46:38 UTC", "videos": 64, "subscribers": 19, "views": 23277 },
  "AJ_Studios": { "date": "2026-06-08 02:46:38 UTC", "videos": 17, "subscribers": 7, "views": 11300 },
  "lokismr": { "date": "2026-06-08 02:46:38 UTC", "videos": 25, "subscribers": 33, "views": 28897 }
}
